iosdebug/__init__.py
iosdebug/__main__.py
iosdebug/constants.py
iosdebug/logger.py
iosdebug/start.py
iosdebug/stop.py
iosdebug/templates.py
iosdebug/processing/__init__.py
iosdebug/processing/create_path_to_content_dict.py
iosdebug/processing/find_swift_files.py
iosdebug/processing/starting/__init__.py
iosdebug/processing/starting/add_mock_registrations_to_container_builder.py
iosdebug/processing/starting/add_run_script_build_phase.py
iosdebug/processing/starting/create_and_set_mock_manager.py
iosdebug/processing/starting/create_basic_mock_implementation.py
iosdebug/processing/starting/find_repository_protocols.py
iosdebug/processing/starting/get_mock_functions_variants.py
iosdebug/processing/starting/get_mock_settings_and_mock_cursor.py
iosdebug/processing/starting/get_original_registration.py
iosdebug/processing/starting/get_protocol_to_mocked_content_dict.py
iosdebug/processing/starting/get_protocols_to_protocol_functions_dict.py
iosdebug/processing/starting/get_registrations.py
iosdebug/processing/starting/get_stored_mock_implementation.py
iosdebug/processing/starting/get_updated_mocked_implementation.py
iosdebug/processing/starting/is_debug_mode_on.py
iosdebug/processing/starting/store_mocked_implementation.py
iosdebug/processing/starting/write_mock_implementations.py
iosdebug/processing/stopping/__init__.py
iosdebug/processing/stopping/remove_mock_registrations.py
iosdebug/processing/stopping/remove_run_script_build_phase.py
iosdebug/processing/stopping/set_original_root_view_controller.py
iosdebug/processing/stopping/store_mocked_implementations.py
ios_debug-0.1.5.dist-info/METADATA
ios_debug-0.1.5.dist-info/WHEEL
ios_debug-0.1.5.dist-info/entry_points.txt
ios_debug-0.1.5.dist-info/top_level.txt
ios_debug-0.1.5.dist-info/RECORD
