Metadata-Version: 2.1
Name: ios-debug
Version: 0.1.5
Summary: Debug mode manager for iOS.
Home-page: UNKNOWN
Author: Tom Novotny
Author-email: tom.novota@gmail.com
License: MIT
Platform: UNKNOWN
Classifier: License :: OSI Approved :: MIT License
Classifier: Programming Language :: Python :: 3
Classifier: Programming Language :: Python :: 3.7
Requires-Dist: prompt-toolkit
Requires-Dist: psutil
Requires-Dist: gitpython
